odoo10_addon_mail_attach_existing_attachment-10.0.1.0.1-py3.8-nspkg.pth
odoo/addons/mail_attach_existing_attachment/README.rst
odoo/addons/mail_attach_existing_attachment/__init__.py
odoo/addons/mail_attach_existing_attachment/__manifest__.py
odoo/addons/mail_attach_existing_attachment/i18n/ca.po
odoo/addons/mail_attach_existing_attachment/i18n/de.po
odoo/addons/mail_attach_existing_attachment/i18n/es.po
odoo/addons/mail_attach_existing_attachment/i18n/es_CO.po
odoo/addons/mail_attach_existing_attachment/i18n/fr.po
odoo/addons/mail_attach_existing_attachment/i18n/hr.po
odoo/addons/mail_attach_existing_attachment/i18n/it.po
odoo/addons/mail_attach_existing_attachment/i18n/mail_attach_existing_attachment.pot
odoo/addons/mail_attach_existing_attachment/i18n/pt_BR.po
odoo/addons/mail_attach_existing_attachment/i18n/sl.po
odoo/addons/mail_attach_existing_attachment/i18n/zh_CN.po
odoo/addons/mail_attach_existing_attachment/static/description/attachment.png
odoo/addons/mail_attach_existing_attachment/static/description/ex_mail_compose_message.png
odoo/addons/mail_attach_existing_attachment/static/description/icon.png
odoo/addons/mail_attach_existing_attachment/tests/__init__.py
odoo/addons/mail_attach_existing_attachment/tests/test_mail_attach_existing_attachment.py
odoo/addons/mail_attach_existing_attachment/wizard/__init__.py
odoo/addons/mail_attach_existing_attachment/wizard/mail_compose_message.py
odoo/addons/mail_attach_existing_attachment/wizard/mail_compose_message_view.xml
odoo10_addon_mail_attach_existing_attachment-10.0.1.0.1.dist-info/METADATA
odoo10_addon_mail_attach_existing_attachment-10.0.1.0.1.dist-info/WHEEL
odoo10_addon_mail_attach_existing_attachment-10.0.1.0.1.dist-info/namespace_packages.txt
odoo10_addon_mail_attach_existing_attachment-10.0.1.0.1.dist-info/top_level.txt
odoo10_addon_mail_attach_existing_attachment-10.0.1.0.1.dist-info/RECORD
